OpenSeaScripts/AssetOptions.py
OpenSeaScripts/OSSBrowser.py
OpenSeaScripts/__init__.py
OpenSeaScripts-1.2.3.dist-info/LICENSE
OpenSeaScripts-1.2.3.dist-info/METADATA
OpenSeaScripts-1.2.3.dist-info/WHEEL
OpenSeaScripts-1.2.3.dist-info/top_level.txt
OpenSeaScripts-1.2.3.dist-info/RECORD
