Metadata-Version: 2.1
Name: OpenSeaScripts
Version: 1.2.3
Summary: Scripts for automating OpenSea operations
Home-page: https://github.com/MRegirouard/OpenSeaScripts
License: UNKNOWN
Platform: UNKNOWN
Classifier: Programming Language :: Python :: 3
Classifier: License :: OSI Approved :: GNU General Public License v3 or later (GPLv3+)
Classifier: Topic :: Internet :: WWW/HTTP :: Browsers
License-File: LICENSE
Requires-Dist: selenium
Requires-Dist: webdriver-manager
